{"Tarjetas": [[{"nombre": "Lewis Ochoa", "partidos_jugados": "2", "tarjetas_amarillas": "0", "tarjetas_rojas": "0", "year": "2005"}], [{"nombre": "C\u00e9sar Augusto Valoyes", "partidos_jugados": "1", "tarjetas_amarillas": "0", "tarjetas_rojas": "0", "year": "2005"}], [{"nombre": "Andr\u00e9s Rodr\u00edguez", "partidos_jugados": "1", "tarjetas_amarillas": "0", "tarjetas_rojas": "0", "year": "2005"}], [{"nombre": "Rodrigo Sebastian Riep", "partidos_jugados": "4", "tarjetas_amarillas": "0", "tarjetas_rojas": "0", "year": "2005"}], [{"nombre": "Juan Pablo Pino", "partidos_jugados": "2", "tarjetas_amarillas": "0", "tarjetas_rojas": "0", "year": "2005"}], [{"nombre": "Jhon Alexander Jaramillo", "partidos_jugados": "1", "tarjetas_amarillas": "0", "tarjetas_rojas": "0", "year": "2005"}], [{"nombre": "Jaime Castrill\u00f3n", "partidos_jugados": "3", "tarjetas_amarillas": "0", "tarjetas_rojas": "0", "year": "2005"}], [{"nombre": "Juan Botero", "partidos_jugados": "1", "tarjetas_amarillas": "0", "tarjetas_rojas": "0", "year": "2005"}], [{"nombre": "Diego Alvarez", "partidos_jugados": "5", "tarjetas_amarillas": "0", "tarjetas_rojas": "0", "year": "2005"}], [{"nombre": "Heriberto Jos\u00e9 Velandia", "partidos_jugados": "2", "tarjetas_amarillas": "0", "tarjetas_rojas": "0", "year": "2005"}], [{"nombre": "Jhon Alexander Valencia", "partidos_jugados": "1", "tarjetas_amarillas": "0", "tarjetas_rojas": "0", "year": "2005"}], [{"nombre": "Roberto Carlos Cort\u00e9s", "partidos_jugados": "4", "tarjetas_amarillas": "0", "tarjetas_rojas": "0", "year": "2005"}], [{"nombre": "Jair Ben\u00edtez", "partidos_jugados": "2", "tarjetas_amarillas": "0", "tarjetas_rojas": "0", "year": "2005"}], [{"nombre": "Luis C\u00f3rdoba", "partidos_jugados": "1", "tarjetas_amarillas": "0", "tarjetas_rojas": "0", "year": "2005"}], [{"nombre": "Andres Mauricio Molina", "partidos_jugados": "1", "tarjetas_amarillas": "0", "tarjetas_rojas": "0", "year": "2006"}], [{"nombre": "Nicol\u00e1s Andr\u00e9s Torres", "partidos_jugados": "13", "tarjetas_amarillas": "0", "tarjetas_rojas": "0", "year": "2006"}], [{"nombre": "Mauricio Molina", "partidos_jugados": "8", "tarjetas_amarillas": "0", "tarjetas_rojas": "0", "year": "2006"}], [{"nombre": "Jos\u00e9 Hermes Mera", "partidos_jugados": "9", "tarjetas_amarillas": "0", "tarjetas_rojas": "0", "year": "2006"}], [{"nombre": "Jhon Alexander Valencia", "partidos_jugados": "3", "tarjetas_amarillas": "0", "tarjetas_rojas": "0", "year": "2006"}], [{"nombre": "Jhann Carlos L\u00f3pez", "partidos_jugados": "4", "tarjetas_amarillas": "0", "tarjetas_rojas": "0", "year": "2006"}], [{"nombre": "Bryan L\u00f3pez Yepes", "partidos_jugados": "9", "tarjetas_amarillas": "0", "tarjetas_rojas": "0", "year": "2007"}], [{"nombre": "Javier Restrepo", "partidos_jugados": "21", "tarjetas_amarillas": "4", "tarjetas_rojas": "2", "year": "2008"}], [{"nombre": "Jamell Ramos", "partidos_jugados": "24", "tarjetas_amarillas": "9", "tarjetas_rojas": "0", "year": "2008"}], [{"nombre": "Luis C\u00f3rdoba", "partidos_jugados": "17", "tarjetas_amarillas": "5", "tarjetas_rojas": "1", "year": "2008"}], [{"nombre": "Omar P\u00e9rez", "partidos_jugados": "20", "tarjetas_amarillas": "3", "tarjetas_rojas": "1", "year": "2008"}], [{"nombre": "Ormedis Madera", "partidos_jugados": "6", "tarjetas_amarillas": "3", "tarjetas_rojas": "1", "year": "2008"}], [{"nombre": "Juan Quintero", "partidos_jugados": "20", "tarjetas_amarillas": "5", "tarjetas_rojas": "0", "year": "2008"}], [{"nombre": "Andr\u00e9s Ortiz", "partidos_jugados": "18", "tarjetas_amarillas": "2", "tarjetas_rojas": "1", "year": "2008"}], [{"nombre": "Juan Ort\u00edz", "partidos_jugados": "18", "tarjetas_amarillas": "4", "tarjetas_rojas": "0", "year": "2008"}], [{"nombre": "Diego Alvarez", "partidos_jugados": "24", "tarjetas_amarillas": "3", "tarjetas_rojas": "0", "year": "2008"}], [{"nombre": "Hern\u00e1n Pert\u00faz", "partidos_jugados": "11", "tarjetas_amarillas": "2", "tarjetas_rojas": "0", "year": "2008"}], [{"nombre": "Iv\u00e1n Corredor", "partidos_jugados": "14", "tarjetas_amarillas": "1", "tarjetas_rojas": "0", "year": "2008"}], [{"nombre": "Juan Muriel", "partidos_jugados": "4", "tarjetas_amarillas": "1", "tarjetas_rojas": "0", "year": "2008"}], [{"nombre": "Aldo Bobadilla", "partidos_jugados": "25", "tarjetas_amarillas": "1", "tarjetas_rojas": "0", "year": "2008"}], [{"nombre": "Ayron del Valle", "partidos_jugados": "8", "tarjetas_amarillas": "0", "tarjetas_rojas": "0", "year": "2008"}], [{"nombre": "Rafael Castillo", "partidos_jugados": "3", "tarjetas_amarillas": "0", "tarjetas_rojas": "0", "year": "2008"}], [{"nombre": "H\u00e9ctor Alejandro Vasco", "partidos_jugados": "1", "tarjetas_amarillas": "0", "tarjetas_rojas": "0", "year": "2008"}], [{"nombre": "Jaime Castrill\u00f3n", "partidos_jugados": "17", "tarjetas_amarillas": "0", "tarjetas_rojas": "0", "year": "2008"}], [{"nombre": "Roger Ca\u00f1as", "partidos_jugados": "3", "tarjetas_amarillas": "0", "tarjetas_rojas": "0", "year": "2008"}], [{"nombre": "Giovanni L\u00f3pez", "partidos_jugados": "1", "tarjetas_amarillas": "0", "tarjetas_rojas": "0", "year": "2008"}], [{"nombre": "Andr\u00e9s Felipe Mosquera", "partidos_jugados": "2", "tarjetas_amarillas": "0", "tarjetas_rojas": "0", "year": "2008"}], [{"nombre": "Elkin Mosquera", "partidos_jugados": "3", "tarjetas_amarillas": "0", "tarjetas_rojas": "0", "year": "2008"}], [{"nombre": "David Andrade Hern\u00e1ndez", "partidos_jugados": "1", "tarjetas_amarillas": "0", "tarjetas_rojas": "0", "year": "2008"}], [{"nombre": "Samuel Antonio Vanegas", "partidos_jugados": "23", "tarjetas_amarillas": "6", "tarjetas_rojas": "2", "year": "2009"}], [{"nombre": "Felipe Pardo", "partidos_jugados": "19", "tarjetas_amarillas": "11", "tarjetas_rojas": "0", "year": "2009"}], [{"nombre": "Juan Valencia", "partidos_jugados": "24", "tarjetas_amarillas": "6", "tarjetas_rojas": "1", "year": "2009"}], [{"nombre": "Leiton Jimenez", "partidos_jugados": "23", "tarjetas_amarillas": "5", "tarjetas_rojas": "1", "year": "2009"}], [{"nombre": "Javier Restrepo", "partidos_jugados": "23", "tarjetas_amarillas": "4", "tarjetas_rojas": "1", "year": "2009"}], [{"nombre": "Juan Ort\u00edz", "partidos_jugados": "24", "tarjetas_amarillas": "7", "tarjetas_rojas": "0", "year": "2009"}], [{"nombre": "Andr\u00e9s Ortiz", "partidos_jugados": "9", "tarjetas_amarillas": "3", "tarjetas_rojas": "1", "year": "2009"}], [{"nombre": "Luis Fernando Mosquera", "partidos_jugados": "22", "tarjetas_amarillas": "2", "tarjetas_rojas": "0", "year": "2009"}], [{"nombre": "Ricardo Calle", "partidos_jugados": "25", "tarjetas_amarillas": "2", "tarjetas_rojas": "0", "year": "2009"}], [{"nombre": "Yohn Geiler Mosquera", "partidos_jugados": "2", "tarjetas_amarillas": "1", "tarjetas_rojas": "0", "year": "2009"}], [{"nombre": "Aldo Bobadilla", "partidos_jugados": "25", "tarjetas_amarillas": "1", "tarjetas_rojas": "0", "year": "2009"}], [{"nombre": "Mauricio Julio", "partidos_jugados": "3", "tarjetas_amarillas": "0", "tarjetas_rojas": "0", "year": "2009"}], [{"nombre": "Jhonatan Andr\u00e9s Cueto", "partidos_jugados": "2", "tarjetas_amarillas": "0", "tarjetas_rojas": "0", "year": "2009"}], [{"nombre": "C\u00e9sar Quintero", "partidos_jugados": "1", "tarjetas_amarillas": "0", "tarjetas_rojas": "0", "year": "2009"}], [{"nombre": "Rafael Castillo", "partidos_jugados": "2", "tarjetas_amarillas": "0", "tarjetas_rojas": "0", "year": "2009"}], [{"nombre": "Juan Muriel", "partidos_jugados": "5", "tarjetas_amarillas": "0", "tarjetas_rojas": "0", "year": "2009"}], [{"nombre": "Hern\u00e1n Pert\u00faz", "partidos_jugados": "5", "tarjetas_amarillas": "0", "tarjetas_rojas": "0", "year": "2009"}], [{"nombre": "Giovanni L\u00f3pez", "partidos_jugados": "5", "tarjetas_amarillas": "0", "tarjetas_rojas": "0", "year": "2009"}], [{"nombre": "Andr\u00e9s Felipe Mosquera", "partidos_jugados": "1", "tarjetas_amarillas": "0", "tarjetas_rojas": "0", "year": "2009"}], [{"nombre": "Elkin Mosquera", "partidos_jugados": "2", "tarjetas_amarillas": "0", "tarjetas_rojas": "0", "year": "2009"}], [{"nombre": "Juan Gomez", "partidos_jugados": "1", "tarjetas_amarillas": "0", "tarjetas_rojas": "0", "year": "2009"}], [{"nombre": "Brayan Lopez", "partidos_jugados": "1", "tarjetas_amarillas": "0", "tarjetas_rojas": "0", "year": "2009"}], [{"nombre": "Juan Ort\u00edz", "partidos_jugados": "15", "tarjetas_amarillas": "3", "tarjetas_rojas": "1", "year": "2010"}], [{"nombre": "Juan Leal", "partidos_jugados": "11", "tarjetas_amarillas": "3", "tarjetas_rojas": "1", "year": "2010"}], [{"nombre": "Lewis Ochoa", "partidos_jugados": "13", "tarjetas_amarillas": "2", "tarjetas_rojas": "1", "year": "2010"}], [{"nombre": "Anselmo Almeida", "partidos_jugados": "17", "tarjetas_amarillas": "5", "tarjetas_rojas": "0", "year": "2010"}], [{"nombre": "Felipe Pardo", "partidos_jugados": "16", "tarjetas_amarillas": "4", "tarjetas_rojas": "0", "year": "2010"}], [{"nombre": "Juan Valencia", "partidos_jugados": "12", "tarjetas_amarillas": "1", "tarjetas_rojas": "1", "year": "2010"}], [{"nombre": "Juan Muriel", "partidos_jugados": "1", "tarjetas_amarillas": "0", "tarjetas_rojas": "1", "year": "2010"}], [{"nombre": "Luis Arias", "partidos_jugados": "16", "tarjetas_amarillas": "2", "tarjetas_rojas": "0", "year": "2010"}], [{"nombre": "H\u00e9ctor Alejandro Vasco", "partidos_jugados": "5", "tarjetas_amarillas": "2", "tarjetas_rojas": "0", "year": "2010"}], [{"nombre": "Leiton Jimenez", "partidos_jugados": "16", "tarjetas_amarillas": "2", "tarjetas_rojas": "0", "year": "2010"}], [{"nombre": "Yohn Geiler Mosquera", "partidos_jugados": "3", "tarjetas_amarillas": "2", "tarjetas_rojas": "0", "year": "2010"}], [{"nombre": "Roberto Cort\u00e9s", "partidos_jugados": "7", "tarjetas_amarillas": "2", "tarjetas_rojas": "0", "year": "2010"}], [{"nombre": "Jhon Edward Hernandez", "partidos_jugados": "5", "tarjetas_amarillas": "1", "tarjetas_rojas": "0", "year": "2010"}], [{"nombre": "Javier Restrepo", "partidos_jugados": "15", "tarjetas_amarillas": "1", "tarjetas_rojas": "0", "year": "2010"}], [{"nombre": "Nelson Barahona", "partidos_jugados": "12", "tarjetas_amarillas": "1", "tarjetas_rojas": "0", "year": "2010"}], [{"nombre": "Giovanni L\u00f3pez", "partidos_jugados": "4", "tarjetas_amarillas": "1", "tarjetas_rojas": "0", "year": "2010"}], [{"nombre": "Ricardo Calle", "partidos_jugados": "11", "tarjetas_amarillas": "1", "tarjetas_rojas": "0", "year": "2010"}], [{"nombre": "Marino Garc\u00eda", "partidos_jugados": "3", "tarjetas_amarillas": "1", "tarjetas_rojas": "0", "year": "2010"}], [{"nombre": "Yorleys Mena", "partidos_jugados": "5", "tarjetas_amarillas": "0", "tarjetas_rojas": "0", "year": "2010"}], [{"nombre": "Hern\u00e1n Pert\u00faz", "partidos_jugados": "16", "tarjetas_amarillas": "0", "tarjetas_rojas": "0", "year": "2010"}], [{"nombre": "Brayan Lopez", "partidos_jugados": "2", "tarjetas_amarillas": "0", "tarjetas_rojas": "0", "year": "2010"}], [{"nombre": "Br\u00e9iner Castillo", "partidos_jugados": "15", "tarjetas_amarillas": "0", "tarjetas_rojas": "0", "year": "2010"}], [{"nombre": "John Bayron Garc\u00eda", "partidos_jugados": "4", "tarjetas_amarillas": "0", "tarjetas_rojas": "0", "year": "2010"}], [{"nombre": "David Alexandre Rancan", "partidos_jugados": "13", "tarjetas_amarillas": "6", "tarjetas_rojas": "2", "year": "2011"}], [{"nombre": "Roberto Cort\u00e9s", "partidos_jugados": "17", "tarjetas_amarillas": "7", "tarjetas_rojas": "1", "year": "2011"}], [{"nombre": "Luis Pitton", "partidos_jugados": "18", "tarjetas_amarillas": "5", "tarjetas_rojas": "0", "year": "2011"}], [{"nombre": "Leiton Jimenez", "partidos_jugados": "14", "tarjetas_amarillas": "2", "tarjetas_rojas": "1", "year": "2011"}], [{"nombre": "Iv\u00e1n Vel\u00e1squez", "partidos_jugados": "13", "tarjetas_amarillas": "3", "tarjetas_rojas": "0", "year": "2011"}], [{"nombre": "Cristian Tabares", "partidos_jugados": "5", "tarjetas_amarillas": "3", "tarjetas_rojas": "0", "year": "2011"}], [{"nombre": "Pablo Desp\u00f3sito", "partidos_jugados": "6", "tarjetas_amarillas": "3", "tarjetas_rojas": "0", "year": "2011"}], [{"nombre": "Francisco C\u00f3rdoba", "partidos_jugados": "13", "tarjetas_amarillas": "3", "tarjetas_rojas": "0", "year": "2011"}], [{"nombre": "Ricardo Calle", "partidos_jugados": "11", "tarjetas_amarillas": "3", "tarjetas_rojas": "0", "year": "2011"}], [{"nombre": "Luis Fernando Mosquera", "partidos_jugados": "16", "tarjetas_amarillas": "2", "tarjetas_rojas": "0", "year": "2011"}], [{"nombre": "C\u00e9sar Augusto Valoyes", "partidos_jugados": "10", "tarjetas_amarillas": "2", "tarjetas_rojas": "0", "year": "2011"}], [{"nombre": "Javier Restrepo", "partidos_jugados": "18", "tarjetas_amarillas": "2", "tarjetas_rojas": "0", "year": "2011"}], [{"nombre": "Felipe Pardo", "partidos_jugados": "12", "tarjetas_amarillas": "2", "tarjetas_rojas": "0", "year": "2011"}], [{"nombre": "Jaime Castrill\u00f3n", "partidos_jugados": "18", "tarjetas_amarillas": "2", "tarjetas_rojas": "0", "year": "2011"}], [{"nombre": "Hern\u00e1n Pert\u00faz", "partidos_jugados": "6", "tarjetas_amarillas": "2", "tarjetas_rojas": "0", "year": "2011"}], [{"nombre": "Yeferson Mena", "partidos_jugados": "2", "tarjetas_amarillas": "1", "tarjetas_rojas": "0", "year": "2011"}], [{"nombre": "Br\u00e9iner Castillo", "partidos_jugados": "17", "tarjetas_amarillas": "1", "tarjetas_rojas": "0", "year": "2011"}], [{"nombre": "John Bayron Garc\u00eda", "partidos_jugados": "1", "tarjetas_amarillas": "1", "tarjetas_rojas": "0", "year": "2011"}], [{"nombre": "Javier Calle", "partidos_jugados": "6", "tarjetas_amarillas": "0", "tarjetas_rojas": "0", "year": "2011"}], [{"nombre": "Jorge Arias", "partidos_jugados": "1", "tarjetas_amarillas": "0", "tarjetas_rojas": "0", "year": "2011"}], [{"nombre": "Jhon Edward Hernandez", "partidos_jugados": "3", "tarjetas_amarillas": "0", "tarjetas_rojas": "0", "year": "2011"}], [{"nombre": "Mauricio Arroyo", "partidos_jugados": "2", "tarjetas_amarillas": "0", "tarjetas_rojas": "0", "year": "2011"}], [{"nombre": "Diego Valdes", "partidos_jugados": "3", "tarjetas_amarillas": "0", "tarjetas_rojas": "0", "year": "2011"}], [{"nombre": "Juan Chaberra", "partidos_jugados": "1", "tarjetas_amarillas": "0", "tarjetas_rojas": "0", "year": "2011"}], [{"nombre": "Brayan Lopez", "partidos_jugados": "1", "tarjetas_amarillas": "0", "tarjetas_rojas": "0", "year": "2011"}], [{"nombre": "John Edwis Vi\u00e1fara", "partidos_jugados": "18", "tarjetas_amarillas": "7", "tarjetas_rojas": "1", "year": "2012"}], [{"nombre": "Felipe Pardo", "partidos_jugados": "22", "tarjetas_amarillas": "6", "tarjetas_rojas": "1", "year": "2012"}], [{"nombre": "Amilcar Henriquez", "partidos_jugados": "22", "tarjetas_amarillas": "9", "tarjetas_rojas": "0", "year": "2012"}], [{"nombre": "William Zapata Brand", "partidos_jugados": "19", "tarjetas_amarillas": "5", "tarjetas_rojas": "1", "year": "2012"}], [{"nombre": "Germ\u00e1n Cano", "partidos_jugados": "19", "tarjetas_amarillas": "2", "tarjetas_rojas": "2", "year": "2012"}], [{"nombre": "Diego Herner", "partidos_jugados": "23", "tarjetas_amarillas": "8", "tarjetas_rojas": "0", "year": "2012"}], [{"nombre": "Daniel Bocanegra", "partidos_jugados": "25", "tarjetas_amarillas": "4", "tarjetas_rojas": "1", "year": "2012"}], [{"nombre": "Jorge Arias", "partidos_jugados": "18", "tarjetas_amarillas": "6", "tarjetas_rojas": "0", "year": "2012"}], [{"nombre": "Juli\u00e1n Guillermo", "partidos_jugados": "23", "tarjetas_amarillas": "6", "tarjetas_rojas": "0", "year": "2012"}], [{"nombre": "Jhonnier Gonz\u00e1lez", "partidos_jugados": "13", "tarjetas_amarillas": "4", "tarjetas_rojas": "0", "year": "2012"}], [{"nombre": "William Arboleda", "partidos_jugados": "18", "tarjetas_amarillas": "3", "tarjetas_rojas": "0", "year": "2012"}], [{"nombre": "Andres Correa Osorio", "partidos_jugados": "26", "tarjetas_amarillas": "3", "tarjetas_rojas": "0", "year": "2012"}], [{"nombre": "Leandro Castellanos", "partidos_jugados": "25", "tarjetas_amarillas": "0", "tarjetas_rojas": "1", "year": "2012"}], [{"nombre": "Sebastian Hernandez", "partidos_jugados": "23", "tarjetas_amarillas": "2", "tarjetas_rojas": "0", "year": "2012"}], [{"nombre": "Yeferson Mena", "partidos_jugados": "18", "tarjetas_amarillas": "2", "tarjetas_rojas": "0", "year": "2012"}], [{"nombre": "Yorleys Mena", "partidos_jugados": "6", "tarjetas_amarillas": "1", "tarjetas_rojas": "0", "year": "2012"}], [{"nombre": "Luis Pitton", "partidos_jugados": "10", "tarjetas_amarillas": "1", "tarjetas_rojas": "0", "year": "2012"}], [{"nombre": "Luis Nu\u00f1ez", "partidos_jugados": "4", "tarjetas_amarillas": "1", "tarjetas_rojas": "0", "year": "2012"}], [{"nombre": "Ray Vanegas", "partidos_jugados": "1", "tarjetas_amarillas": "0", "tarjetas_rojas": "0", "year": "2012"}], [{"nombre": "Jhon Qui\u00f1ones", "partidos_jugados": "2", "tarjetas_amarillas": "0", "tarjetas_rojas": "0", "year": "2012"}], [{"nombre": "Leonardo Ossa", "partidos_jugados": "3", "tarjetas_amarillas": "0", "tarjetas_rojas": "0", "year": "2012"}], [{"nombre": "Jhon Edward Hernandez", "partidos_jugados": "4", "tarjetas_amarillas": "0", "tarjetas_rojas": "0", "year": "2012"}], [{"nombre": "Andr\u00e9s Ortiz", "partidos_jugados": "1", "tarjetas_amarillas": "0", "tarjetas_rojas": "0", "year": "2012"}], [{"nombre": "Ricardo Calle", "partidos_jugados": "2", "tarjetas_amarillas": "0", "tarjetas_rojas": "0", "year": "2012"}], [{"nombre": "Carlos Bejarano", "partidos_jugados": "2", "tarjetas_amarillas": "0", "tarjetas_rojas": "0", "year": "2012"}], [{"nombre": "Jorge Arias", "partidos_jugados": "10", "tarjetas_amarillas": "2", "tarjetas_rojas": "1", "year": "2013"}], [{"nombre": "Diego Herner", "partidos_jugados": "17", "tarjetas_amarillas": "3", "tarjetas_rojas": "0", "year": "2013"}], [{"nombre": "Germ\u00e1n Cano", "partidos_jugados": "12", "tarjetas_amarillas": "2", "tarjetas_rojas": "0", "year": "2013"}], [{"nombre": "Andres Correa Osorio", "partidos_jugados": "6", "tarjetas_amarillas": "1", "tarjetas_rojas": "0", "year": "2013"}], [{"nombre": "Cleider Alzate", "partidos_jugados": "18", "tarjetas_amarillas": "1", "tarjetas_rojas": "0", "year": "2013"}], [{"nombre": "Amilcar Henriquez", "partidos_jugados": "1", "tarjetas_amarillas": "1", "tarjetas_rojas": "0", "year": "2013"}], [{"nombre": "Andr\u00e9s Felipe Mosquera", "partidos_jugados": "6", "tarjetas_amarillas": "1", "tarjetas_rojas": "0", "year": "2013"}], [{"nombre": "Ray Vanegas", "partidos_jugados": "0", "tarjetas_amarillas": "0", "tarjetas_rojas": "0", "year": "2013"}], [{"nombre": "Yuli\u00e1n Mej\u00eda", "partidos_jugados": "1", "tarjetas_amarillas": "0", "tarjetas_rojas": "0", "year": "2013"}], [{"nombre": "Cristian Restrepo", "partidos_jugados": "1", "tarjetas_amarillas": "0", "tarjetas_rojas": "0", "year": "2013"}], [{"nombre": "Dager Palacios", "partidos_jugados": "1", "tarjetas_amarillas": "0", "tarjetas_rojas": "0", "year": "2013"}], [{"nombre": "Jhon Hern\u00e1ndez", "partidos_jugados": "1", "tarjetas_amarillas": "0", "tarjetas_rojas": "0", "year": "2013"}], [{"nombre": "Juan Pablo Zuluaga", "partidos_jugados": "3", "tarjetas_amarillas": "0", "tarjetas_rojas": "0", "year": "2013"}], [{"nombre": "Dairon Mosquera", "partidos_jugados": "1", "tarjetas_amarillas": "0", "tarjetas_rojas": "0", "year": "2013"}], [{"nombre": "Hern\u00e1n Pert\u00faz", "partidos_jugados": "1", "tarjetas_amarillas": "0", "tarjetas_rojas": "0", "year": "2013"}], [{"nombre": "Carlos Bejarano", "partidos_jugados": "0", "tarjetas_amarillas": "0", "tarjetas_rojas": "0", "year": "2013"}], [{"nombre": "Leandro Castellanos", "partidos_jugados": "1", "tarjetas_amarillas": "0", "tarjetas_rojas": "0", "year": "2013"}], [{"nombre": "Vladimir Mar\u00edn", "partidos_jugados": "19", "tarjetas_amarillas": "9", "tarjetas_rojas": "1", "year": "2014"}], [{"nombre": "Jherson C\u00f3rdoba", "partidos_jugados": "23", "tarjetas_amarillas": "9", "tarjetas_rojas": "0", "year": "2014"}], [{"nombre": "Jhon Hern\u00e1ndez", "partidos_jugados": "19", "tarjetas_amarillas": "8", "tarjetas_rojas": "0", "year": "2014"}], [{"nombre": "Cristian Restrepo", "partidos_jugados": "17", "tarjetas_amarillas": "4", "tarjetas_rojas": "1", "year": "2014"}], [{"nombre": "Diego Herner", "partidos_jugados": "11", "tarjetas_amarillas": "4", "tarjetas_rojas": "1", "year": "2014"}], [{"nombre": "Carlos Valencia", "partidos_jugados": "16", "tarjetas_amarillas": "5", "tarjetas_rojas": "0", "year": "2014"}], [{"nombre": "Jefferson Mena", "partidos_jugados": "14", "tarjetas_amarillas": "4", "tarjetas_rojas": "0", "year": "2014"}], [{"nombre": "Luis Tipton", "partidos_jugados": "8", "tarjetas_amarillas": "4", "tarjetas_rojas": "0", "year": "2014"}], [{"nombre": "Juli\u00e1n Guillermo", "partidos_jugados": "9", "tarjetas_amarillas": "3", "tarjetas_rojas": "0", "year": "2014"}], [{"nombre": "Andres Mosquera", "partidos_jugados": "25", "tarjetas_amarillas": "3", "tarjetas_rojas": "0", "year": "2014"}], [{"nombre": "Carlos Bejarano", "partidos_jugados": "17", "tarjetas_amarillas": "3", "tarjetas_rojas": "0", "year": "2014"}], [{"nombre": "Javier Calle", "partidos_jugados": "19", "tarjetas_amarillas": "1", "tarjetas_rojas": "0", "year": "2014"}], [{"nombre": "Christian Marrugo", "partidos_jugados": "22", "tarjetas_amarillas": "1", "tarjetas_rojas": "0", "year": "2014"}], [{"nombre": "Daniel Hern\u00e1ndez", "partidos_jugados": "24", "tarjetas_amarillas": "1", "tarjetas_rojas": "0", "year": "2014"}], [{"nombre": "Leonel Garc\u00eda", "partidos_jugados": "0", "tarjetas_amarillas": "0", "tarjetas_rojas": "0", "year": "2014"}], [{"nombre": "Elton", "partidos_jugados": "16", "tarjetas_amarillas": "0", "tarjetas_rojas": "0", "year": "2014"}], [{"nombre": "William Arboleda", "partidos_jugados": "3", "tarjetas_amarillas": "0", "tarjetas_rojas": "0", "year": "2014"}], [{"nombre": "Gilberto Garc\u00eda", "partidos_jugados": "11", "tarjetas_amarillas": "0", "tarjetas_rojas": "0", "year": "2014"}], [{"nombre": "Jorge Arias", "partidos_jugados": "0", "tarjetas_amarillas": "0", "tarjetas_rojas": "0", "year": "2014"}], [{"nombre": "Hern\u00e1n Pert\u00faz", "partidos_jugados": "13", "tarjetas_amarillas": "0", "tarjetas_rojas": "0", "year": "2014"}], [{"nombre": "Diego Amaya", "partidos_jugados": "1", "tarjetas_amarillas": "0", "tarjetas_rojas": "0", "year": "2014"}], [{"nombre": "Juan Juan G\u00f3mez", "partidos_jugados": "0", "tarjetas_amarillas": "0", "tarjetas_rojas": "0", "year": "2014"}], [{"nombre": "Leandro Castellanos", "partidos_jugados": "9", "tarjetas_amarillas": "0", "tarjetas_rojas": "0", "year": "2014"}], [{"nombre": "Luis V\u00e1squez", "partidos_jugados": "0", "tarjetas_amarillas": "0", "tarjetas_rojas": "0", "year": "2014"}], [{"nombre": "Didier Moreno", "partidos_jugados": "63", "tarjetas_amarillas": "27", "tarjetas_rojas": "0", "year": "2015"}], [{"nombre": "Frank Fabra", "partidos_jugados": "54", "tarjetas_amarillas": "9", "tarjetas_rojas": "6", "year": "2015"}], [{"nombre": "Johan Arango", "partidos_jugados": "60", "tarjetas_amarillas": "21", "tarjetas_rojas": "0", "year": "2015"}], [{"nombre": "Daniel Torres", "partidos_jugados": "69", "tarjetas_amarillas": "18", "tarjetas_rojas": "0", "year": "2015"}], [{"nombre": "Mat\u00edas Cahais", "partidos_jugados": "48", "tarjetas_amarillas": "18", "tarjetas_rojas": "0", "year": "2015"}], [{"nombre": "Andres Mosquera", "partidos_jugados": "60", "tarjetas_amarillas": "9", "tarjetas_rojas": "3", "year": "2015"}], [{"nombre": "Jhon Pajoy", "partidos_jugados": "45", "tarjetas_amarillas": "12", "tarjetas_rojas": "0", "year": "2015"}], [{"nombre": "Christian Marrugo", "partidos_jugados": "63", "tarjetas_amarillas": "3", "tarjetas_rojas": "3", "year": "2015"}], [{"nombre": "Yilmar Alonso Angulo", "partidos_jugados": "18", "tarjetas_amarillas": "0", "tarjetas_rojas": "3", "year": "2015"}], [{"nombre": "Jorge Arias", "partidos_jugados": "57", "tarjetas_amarillas": "9", "tarjetas_rojas": "0", "year": "2015"}], [{"nombre": "Jhon Hern\u00e1ndez", "partidos_jugados": "36", "tarjetas_amarillas": "6", "tarjetas_rojas": "0", "year": "2015"}], [{"nombre": "Hern\u00e1n Pert\u00faz", "partidos_jugados": "30", "tarjetas_amarillas": "6", "tarjetas_rojas": "0", "year": "2015"}], [{"nombre": "Juan Angulo", "partidos_jugados": "13", "tarjetas_amarillas": "4", "tarjetas_rojas": "0", "year": "2015"}], [{"nombre": "Brayan Angulo", "partidos_jugados": "45", "tarjetas_amarillas": "3", "tarjetas_rojas": "0", "year": "2015"}], [{"nombre": "Luis Tipton", "partidos_jugados": "21", "tarjetas_amarillas": "3", "tarjetas_rojas": "0", "year": "2015"}], [{"nombre": "David Gonz\u00e1lez", "partidos_jugados": "42", "tarjetas_amarillas": "3", "tarjetas_rojas": "0", "year": "2015"}], [{"nombre": "Wilson L\u00f3pez", "partidos_jugados": "3", "tarjetas_amarillas": "0", "tarjetas_rojas": "0", "year": "2015"}], [{"nombre": "F\u00e9lix Micolta", "partidos_jugados": "27", "tarjetas_amarillas": "0", "tarjetas_rojas": "0", "year": "2015"}], [{"nombre": "Hern\u00e1n Hechalar", "partidos_jugados": "51", "tarjetas_amarillas": "0", "tarjetas_rojas": "0", "year": "2015"}], [{"nombre": "Ever Valencia", "partidos_jugados": "6", "tarjetas_amarillas": "0", "tarjetas_rojas": "0", "year": "2015"}], [{"nombre": "Sebasti\u00e1n Macias", "partidos_jugados": "9", "tarjetas_amarillas": "0", "tarjetas_rojas": "0", "year": "2015"}], [{"nombre": "Juan Saiz", "partidos_jugados": "3", "tarjetas_amarillas": "0", "tarjetas_rojas": "0", "year": "2015"}], [{"nombre": "Elacio C\u00f3rdoba", "partidos_jugados": "15", "tarjetas_amarillas": "0", "tarjetas_rojas": "0", "year": "2015"}], [{"nombre": "Luis V\u00e1squez", "partidos_jugados": "0", "tarjetas_amarillas": "0", "tarjetas_rojas": "0", "year": "2015"}], [{"nombre": "Juan Cabezas", "partidos_jugados": "19", "tarjetas_amarillas": "5", "tarjetas_rojas": "1", "year": "2016"}], [{"nombre": "Didier Moreno", "partidos_jugados": "15", "tarjetas_amarillas": "7", "tarjetas_rojas": "0", "year": "2016"}], [{"nombre": "Marlon Piedrahita", "partidos_jugados": "18", "tarjetas_amarillas": "4", "tarjetas_rojas": "1", "year": "2016"}], [{"nombre": "Johan Arango", "partidos_jugados": "16", "tarjetas_amarillas": "3", "tarjetas_rojas": "1", "year": "2016"}], [{"nombre": "Mat\u00edas Cahais", "partidos_jugados": "15", "tarjetas_amarillas": "6", "tarjetas_rojas": "0", "year": "2016"}], [{"nombre": "Juan Quintero", "partidos_jugados": "16", "tarjetas_amarillas": "5", "tarjetas_rojas": "0", "year": "2016"}], [{"nombre": "Jhon Hern\u00e1ndez", "partidos_jugados": "15", "tarjetas_amarillas": "4", "tarjetas_rojas": "0", "year": "2016"}], [{"nombre": "Juan Saiz", "partidos_jugados": "12", "tarjetas_amarillas": "4", "tarjetas_rojas": "0", "year": "2016"}], [{"nombre": "Andres Mosquera", "partidos_jugados": "12", "tarjetas_amarillas": "3", "tarjetas_rojas": "0", "year": "2016"}], [{"nombre": "Mauricio Molina", "partidos_jugados": "20", "tarjetas_amarillas": "1", "tarjetas_rojas": "0", "year": "2016"}], [{"nombre": "Sebasti\u00e1n Macias", "partidos_jugados": "5", "tarjetas_amarillas": "1", "tarjetas_rojas": "0", "year": "2016"}], [{"nombre": "Luis Tipton", "partidos_jugados": "5", "tarjetas_amarillas": "1", "tarjetas_rojas": "0", "year": "2016"}], [{"nombre": "Hern\u00e1n Pert\u00faz", "partidos_jugados": "15", "tarjetas_amarillas": "1", "tarjetas_rojas": "0", "year": "2016"}], [{"nombre": "Luis V\u00e1squez", "partidos_jugados": "3", "tarjetas_amarillas": "1", "tarjetas_rojas": "0", "year": "2016"}], [{"nombre": "Juan Felipe Santa", "partidos_jugados": "2", "tarjetas_amarillas": "0", "tarjetas_rojas": "0", "year": "2016"}], [{"nombre": "William Parra", "partidos_jugados": "4", "tarjetas_amarillas": "0", "tarjetas_rojas": "0", "year": "2016"}], [{"nombre": "Daniel Torres", "partidos_jugados": "2", "tarjetas_amarillas": "0", "tarjetas_rojas": "0", "year": "2016"}], [{"nombre": "Hern\u00e1n Hechalar", "partidos_jugados": "18", "tarjetas_amarillas": "0", "tarjetas_rojas": "0", "year": "2016"}], [{"nombre": "Christian Marrugo", "partidos_jugados": "19", "tarjetas_amarillas": "0", "tarjetas_rojas": "0", "year": "2016"}], [{"nombre": "Jhohan Roma\u00f1a", "partidos_jugados": "1", "tarjetas_amarillas": "0", "tarjetas_rojas": "0", "year": "2016"}], [{"nombre": "Ever Valencia", "partidos_jugados": "3", "tarjetas_amarillas": "0", "tarjetas_rojas": "0", "year": "2016"}], [{"nombre": "Elacio C\u00f3rdoba", "partidos_jugados": "4", "tarjetas_amarillas": "0", "tarjetas_rojas": "0", "year": "2016"}], [{"nombre": "Aldair Quintana", "partidos_jugados": "1", "tarjetas_amarillas": "0", "tarjetas_rojas": "0", "year": "2016"}], [{"nombre": "David Gonz\u00e1lez", "partidos_jugados": "19", "tarjetas_amarillas": "0", "tarjetas_rojas": "0", "year": "2016"}], [{"nombre": "Eduard Atuesta", "partidos_jugados": "16", "tarjetas_amarillas": "6", "tarjetas_rojas": "1", "year": "2017"}], [{"nombre": "Didier Moreno", "partidos_jugados": "19", "tarjetas_amarillas": "6", "tarjetas_rojas": "1", "year": "2017"}], [{"nombre": "Santiago Echeverr\u00eda", "partidos_jugados": "15", "tarjetas_amarillas": "8", "tarjetas_rojas": "0", "year": "2017"}], [{"nombre": "Leonardo Castro", "partidos_jugados": "18", "tarjetas_amarillas": "5", "tarjetas_rojas": "0", "year": "2017"}], [{"nombre": "Daniel Cata\u00f1o", "partidos_jugados": "17", "tarjetas_amarillas": "4", "tarjetas_rojas": "0", "year": "2017"}], [{"nombre": "Rodrigo Erramuspe", "partidos_jugados": "13", "tarjetas_amarillas": "4", "tarjetas_rojas": "0", "year": "2017"}], [{"nombre": "Juan Caicedo", "partidos_jugados": "13", "tarjetas_amarillas": "2", "tarjetas_rojas": "0", "year": "2017"}], [{"nombre": "Yairo Moreno", "partidos_jugados": "10", "tarjetas_amarillas": "2", "tarjetas_rojas": "0", "year": "2017"}], [{"nombre": "Yuli\u00e1n G\u00f3mez", "partidos_jugados": "6", "tarjetas_amarillas": "2", "tarjetas_rojas": "0", "year": "2017"}], [{"nombre": "Elacio C\u00f3rdoba", "partidos_jugados": "6", "tarjetas_amarillas": "2", "tarjetas_rojas": "0", "year": "2017"}], [{"nombre": "David Gonz\u00e1lez", "partidos_jugados": "18", "tarjetas_amarillas": "2", "tarjetas_rojas": "0", "year": "2017"}], [{"nombre": "Andr\u00e9s Mosquera", "partidos_jugados": "18", "tarjetas_amarillas": "2", "tarjetas_rojas": "0", "year": "2017"}], [{"nombre": "Jhon Hern\u00e1ndez", "partidos_jugados": "13", "tarjetas_amarillas": "1", "tarjetas_rojas": "0", "year": "2017"}], [{"nombre": "Sebasti\u00e1n Macias", "partidos_jugados": "3", "tarjetas_amarillas": "1", "tarjetas_rojas": "0", "year": "2017"}], [{"nombre": "Hern\u00e1n Pert\u00faz", "partidos_jugados": "5", "tarjetas_amarillas": "1", "tarjetas_rojas": "0", "year": "2017"}], [{"nombre": "John Garc\u00eda", "partidos_jugados": "0", "tarjetas_amarillas": "0", "tarjetas_rojas": "0", "year": "2017"}], [{"nombre": "Daniel Restrepo", "partidos_jugados": "2", "tarjetas_amarillas": "0", "tarjetas_rojas": "0", "year": "2017"}], [{"nombre": "Gerson Valencia", "partidos_jugados": "5", "tarjetas_amarillas": "0", "tarjetas_rojas": "0", "year": "2017"}], [{"nombre": "Jaime Giraldo", "partidos_jugados": "1", "tarjetas_amarillas": "0", "tarjetas_rojas": "0", "year": "2017"}], [{"nombre": "Gabriel D\u00edaz", "partidos_jugados": "0", "tarjetas_amarillas": "0", "tarjetas_rojas": "0", "year": "2017"}], [{"nombre": "Carlos Valencia", "partidos_jugados": "4", "tarjetas_amarillas": "0", "tarjetas_rojas": "0", "year": "2017"}], [{"nombre": "Yimy G\u00f3mez", "partidos_jugados": "0", "tarjetas_amarillas": "0", "tarjetas_rojas": "0", "year": "2017"}], [{"nombre": "Elvis Perlaza", "partidos_jugados": "22", "tarjetas_amarillas": "7", "tarjetas_rojas": "1", "year": "2018"}], [{"nombre": "Jes\u00fas Murillo", "partidos_jugados": "24", "tarjetas_amarillas": "8", "tarjetas_rojas": "0", "year": "2018"}], [{"nombre": "Larry Angulo", "partidos_jugados": "18", "tarjetas_amarillas": "7", "tarjetas_rojas": "0", "year": "2018"}], [{"nombre": "Andr\u00e9s Ricaurte", "partidos_jugados": "24", "tarjetas_amarillas": "6", "tarjetas_rojas": "0", "year": "2018"}], [{"nombre": "Yuli\u00e1n Anchico", "partidos_jugados": "21", "tarjetas_amarillas": "6", "tarjetas_rojas": "0", "year": "2018"}], [{"nombre": "Luis Luna", "partidos_jugados": "15", "tarjetas_amarillas": "5", "tarjetas_rojas": "0", "year": "2018"}], [{"nombre": "William Parra", "partidos_jugados": "17", "tarjetas_amarillas": "4", "tarjetas_rojas": "0", "year": "2018"}], [{"nombre": "Leonardo Castro", "partidos_jugados": "12", "tarjetas_amarillas": "3", "tarjetas_rojas": "0", "year": "2018"}], [{"nombre": "Ever Valencia", "partidos_jugados": "6", "tarjetas_amarillas": "3", "tarjetas_rojas": "0", "year": "2018"}], [{"nombre": "Sebasti\u00e1n Macias", "partidos_jugados": "11", "tarjetas_amarillas": "3", "tarjetas_rojas": "0", "year": "2018"}], [{"nombre": "Jorge Segura", "partidos_jugados": "15", "tarjetas_amarillas": "3", "tarjetas_rojas": "0", "year": "2018"}], [{"nombre": "Javier Calle", "partidos_jugados": "7", "tarjetas_amarillas": "2", "tarjetas_rojas": "0", "year": "2018"}], [{"nombre": "Elvis Mosquera", "partidos_jugados": "18", "tarjetas_amarillas": "2", "tarjetas_rojas": "0", "year": "2018"}], [{"nombre": "Jonathan Barboza", "partidos_jugados": "7", "tarjetas_amarillas": "1", "tarjetas_rojas": "0", "year": "2018"}], [{"nombre": "Juli\u00e1n Lemos", "partidos_jugados": "1", "tarjetas_amarillas": "1", "tarjetas_rojas": "0", "year": "2018"}], [{"nombre": "David Gonz\u00e1lez", "partidos_jugados": "25", "tarjetas_amarillas": "1", "tarjetas_rojas": "0", "year": "2018"}], [{"nombre": "Jhojan Valbuena", "partidos_jugados": "2", "tarjetas_amarillas": "0", "tarjetas_rojas": "0", "year": "2018"}], [{"nombre": "Alejandro B\u00e1rbaro", "partidos_jugados": "3", "tarjetas_amarillas": "0", "tarjetas_rojas": "0", "year": "2018"}], [{"nombre": "Juan D\u00edaz", "partidos_jugados": "0", "tarjetas_amarillas": "0", "tarjetas_rojas": "0", "year": "2018"}], [{"nombre": "Guillermo Tegue", "partidos_jugados": "0", "tarjetas_amarillas": "0", "tarjetas_rojas": "0", "year": "2018"}], [{"nombre": "Hern\u00e1n Pert\u00faz", "partidos_jugados": "18", "tarjetas_amarillas": "0", "tarjetas_rojas": "0", "year": "2018"}], [{"nombre": "Yimy G\u00f3mez", "partidos_jugados": "0", "tarjetas_amarillas": "0", "tarjetas_rojas": "0", "year": "2018"}], [{"nombre": "Andr\u00e9s Mosquera", "partidos_jugados": "0", "tarjetas_amarillas": "0", "tarjetas_rojas": "0", "year": "2018"}], [{"nombre": "Jes\u00fas Murillo", "partidos_jugados": "37", "tarjetas_amarillas": "14", "tarjetas_rojas": "0", "year": "2019"}], [{"nombre": "Elvis Perlaza", "partidos_jugados": "29", "tarjetas_amarillas": "8", "tarjetas_rojas": "1", "year": "2019"}], [{"nombre": "Didier Delgado", "partidos_jugados": "21", "tarjetas_amarillas": "5", "tarjetas_rojas": "1", "year": "2019"}], [{"nombre": "H\u00e9ctor Urrego", "partidos_jugados": "18", "tarjetas_amarillas": "8", "tarjetas_rojas": "0", "year": "2019"}], [{"nombre": "Andr\u00e9s Ricaurte", "partidos_jugados": "37", "tarjetas_amarillas": "7", "tarjetas_rojas": "0", "year": "2019"}], [{"nombre": "Adri\u00e1n Arregui", "partidos_jugados": "17", "tarjetas_amarillas": "6", "tarjetas_rojas": "0", "year": "2019"}], [{"nombre": "Diego Arias", "partidos_jugados": "23", "tarjetas_amarillas": "6", "tarjetas_rojas": "0", "year": "2019"}], [{"nombre": "Didier Moreno", "partidos_jugados": "14", "tarjetas_amarillas": "6", "tarjetas_rojas": "0", "year": "2019"}], [{"nombre": "Jonathan Marulanda", "partidos_jugados": "18", "tarjetas_amarillas": "5", "tarjetas_rojas": "0", "year": "2019"}], [{"nombre": "Andres Cadavid", "partidos_jugados": "18", "tarjetas_amarillas": "5", "tarjetas_rojas": "0", "year": "2019"}], [{"nombre": "Deiner Qui\u00f1\u00f3nez", "partidos_jugados": "16", "tarjetas_amarillas": "3", "tarjetas_rojas": "0", "year": "2019"}], [{"nombre": "Nicolas Palacios", "partidos_jugados": "15", "tarjetas_amarillas": "3", "tarjetas_rojas": "0", "year": "2019"}], [{"nombre": "Dairon Mosquera", "partidos_jugados": "12", "tarjetas_amarillas": "3", "tarjetas_rojas": "0", "year": "2019"}], [{"nombre": "Wilson L\u00f3pez", "partidos_jugados": "7", "tarjetas_amarillas": "1", "tarjetas_rojas": "0", "year": "2019"}], [{"nombre": "Daniel Castro", "partidos_jugados": "2", "tarjetas_amarillas": "1", "tarjetas_rojas": "0", "year": "2019"}], [{"nombre": "William Arboleda", "partidos_jugados": "8", "tarjetas_amarillas": "0", "tarjetas_rojas": "0", "year": "2019"}], [{"nombre": "Juan D\u00edaz", "partidos_jugados": "3", "tarjetas_amarillas": "0", "tarjetas_rojas": "0", "year": "2019"}], [{"nombre": "Estiven Cardona", "partidos_jugados": "0", "tarjetas_amarillas": "0", "tarjetas_rojas": "0", "year": "2019"}], [{"nombre": "Brayan Carabali", "partidos_jugados": "0", "tarjetas_amarillas": "0", "tarjetas_rojas": "0", "year": "2019"}], [{"nombre": "Guillermo Tegue", "partidos_jugados": "10", "tarjetas_amarillas": "0", "tarjetas_rojas": "0", "year": "2019"}], [{"nombre": "Jaime Giraldo", "partidos_jugados": "9", "tarjetas_amarillas": "0", "tarjetas_rojas": "0", "year": "2019"}], [{"nombre": "Hern\u00e1n Pert\u00faz", "partidos_jugados": "2", "tarjetas_amarillas": "0", "tarjetas_rojas": "0", "year": "2019"}], [{"nombre": "Esteban Ruiz", "partidos_jugados": "0", "tarjetas_amarillas": "0", "tarjetas_rojas": "0", "year": "2019"}], [{"nombre": "Andr\u00e9s Mosquera", "partidos_jugados": "1", "tarjetas_amarillas": "0", "tarjetas_rojas": "0", "year": "2019"}], [{"nombre": "Andr\u00e9s Ricaurte", "partidos_jugados": "7", "tarjetas_amarillas": "4", "tarjetas_rojas": "0", "year": "2020"}], [{"nombre": "Jes\u00fas Murillo", "partidos_jugados": "9", "tarjetas_amarillas": "4", "tarjetas_rojas": "0", "year": "2020"}], [{"nombre": "Jos\u00e9 Hern\u00e1ndez", "partidos_jugados": "17", "tarjetas_amarillas": "6", "tarjetas_rojas": "1", "year": "2021"}], [{"nombre": "Adri\u00e1n Arregui", "partidos_jugados": "16", "tarjetas_amarillas": "5", "tarjetas_rojas": "1", "year": "2021"}], [{"nombre": "David Loaiza", "partidos_jugados": "16", "tarjetas_amarillas": "6", "tarjetas_rojas": "0", "year": "2021"}], [{"nombre": "Juan Guillermo Arboleda", "partidos_jugados": "18", "tarjetas_amarillas": "3", "tarjetas_rojas": "1", "year": "2021"}], [{"nombre": "Andres Cadavid", "partidos_jugados": "17", "tarjetas_amarillas": "6", "tarjetas_rojas": "0", "year": "2021"}], [{"nombre": "Germ\u00e1n Guti\u00e9rrez", "partidos_jugados": "19", "tarjetas_amarillas": "5", "tarjetas_rojas": "0", "year": "2021"}], [{"nombre": "Didier Bueno", "partidos_jugados": "9", "tarjetas_amarillas": "2", "tarjetas_rojas": "0", "year": "2021"}], [{"nombre": "Victor Moreno", "partidos_jugados": "7", "tarjetas_amarillas": "2", "tarjetas_rojas": "0", "year": "2021"}], [{"nombre": "Yesid D\u00edaz", "partidos_jugados": "3", "tarjetas_amarillas": "1", "tarjetas_rojas": "0", "year": "2021"}], [{"nombre": "Sebasti\u00e1n Hern\u00e1ndez", "partidos_jugados": "9", "tarjetas_amarillas": "1", "tarjetas_rojas": "0", "year": "2021"}], [{"nombre": "Kevin Londo\u00f1o", "partidos_jugados": "9", "tarjetas_amarillas": "1", "tarjetas_rojas": "0", "year": "2021"}], [{"nombre": "Juan D\u00edaz", "partidos_jugados": "11", "tarjetas_amarillas": "1", "tarjetas_rojas": "0", "year": "2021"}], [{"nombre": "Juan Mosquera", "partidos_jugados": "6", "tarjetas_amarillas": "1", "tarjetas_rojas": "0", "year": "2021"}], [{"nombre": "Andr\u00e9s Mosquera", "partidos_jugados": "17", "tarjetas_amarillas": "1", "tarjetas_rojas": "0", "year": "2021"}], [{"nombre": "Miguel Camargo", "partidos_jugados": "3", "tarjetas_amarillas": "0", "tarjetas_rojas": "0", "year": "2021"}], [{"nombre": "Vladimir Hern\u00e1ndez", "partidos_jugados": "19", "tarjetas_amarillas": "0", "tarjetas_rojas": "0", "year": "2021"}], [{"nombre": "Juan Ospina", "partidos_jugados": "4", "tarjetas_amarillas": "0", "tarjetas_rojas": "0", "year": "2021"}], [{"nombre": "Estiven Cardona", "partidos_jugados": "0", "tarjetas_amarillas": "0", "tarjetas_rojas": "0", "year": "2021"}], [{"nombre": "Yuli\u00e1n G\u00f3mez", "partidos_jugados": "2", "tarjetas_amarillas": "0", "tarjetas_rojas": "0", "year": "2021"}], [{"nombre": "Leit\u00f3n Jim\u00e9nez", "partidos_jugados": "2", "tarjetas_amarillas": "0", "tarjetas_rojas": "0", "year": "2021"}], [{"nombre": "Juan Aguilar", "partidos_jugados": "1", "tarjetas_amarillas": "0", "tarjetas_rojas": "0", "year": "2021"}], [{"nombre": "Gabriel Andr\u00e9s Bran Ruiz", "partidos_jugados": "0", "tarjetas_amarillas": "0", "tarjetas_rojas": "0", "year": "2021"}], [{"nombre": "Yimy G\u00f3mez", "partidos_jugados": "0", "tarjetas_amarillas": "0", "tarjetas_rojas": "0", "year": "2021"}], [{"nombre": "Luis V\u00e1squez", "partidos_jugados": "2", "tarjetas_amarillas": "0", "tarjetas_rojas": "0", "year": "2021"}], [{"nombre": "Adri\u00e1n Arregui", "partidos_jugados": "47", "tarjetas_amarillas": "17", "tarjetas_rojas": "0", "year": "2022"}], [{"nombre": "Andres Cadavid", "partidos_jugados": "45", "tarjetas_amarillas": "16", "tarjetas_rojas": "0", "year": "2022"}], [{"nombre": "Luciano Pons", "partidos_jugados": "49", "tarjetas_amarillas": "9", "tarjetas_rojas": "1", "year": "2022"}], [{"nombre": "Victor Moreno", "partidos_jugados": "47", "tarjetas_amarillas": "8", "tarjetas_rojas": "1", "year": "2022"}], [{"nombre": "Juan Guillermo Arboleda", "partidos_jugados": "43", "tarjetas_amarillas": "10", "tarjetas_rojas": "0", "year": "2022"}], [{"nombre": "Jaen Pineda", "partidos_jugados": "41", "tarjetas_amarillas": "8", "tarjetas_rojas": "0", "year": "2022"}], [{"nombre": "Andr\u00e9s Ricaurte", "partidos_jugados": "38", "tarjetas_amarillas": "5", "tarjetas_rojas": "1", "year": "2022"}], [{"nombre": "Felipe Pardo", "partidos_jugados": "42", "tarjetas_amarillas": "5", "tarjetas_rojas": "1", "year": "2022"}], [{"nombre": "Jorge Segura", "partidos_jugados": "19", "tarjetas_amarillas": "6", "tarjetas_rojas": "0", "year": "2022"}], [{"nombre": "Germ\u00e1n Guti\u00e9rrez", "partidos_jugados": "24", "tarjetas_amarillas": "3", "tarjetas_rojas": "1", "year": "2022"}], [{"nombre": "David Loaiza", "partidos_jugados": "22", "tarjetas_amarillas": "5", "tarjetas_rojas": "0", "year": "2022"}], [{"nombre": "Andr\u00e9s Mosquera", "partidos_jugados": "44", "tarjetas_amarillas": "2", "tarjetas_rojas": "1", "year": "2022"}], [{"nombre": "Javier M\u00e9ndez", "partidos_jugados": "30", "tarjetas_amarillas": "4", "tarjetas_rojas": "0", "year": "2022"}], [{"nombre": "Vladimir Hern\u00e1ndez", "partidos_jugados": "48", "tarjetas_amarillas": "3", "tarjetas_rojas": "0", "year": "2022"}], [{"nombre": "Daniel Torres", "partidos_jugados": "17", "tarjetas_amarillas": "3", "tarjetas_rojas": "0", "year": "2022"}], [{"nombre": "Miguel Monsalve", "partidos_jugados": "9", "tarjetas_amarillas": "2", "tarjetas_rojas": "0", "year": "2022"}], [{"nombre": "Jos\u00e9 Hern\u00e1ndez", "partidos_jugados": "24", "tarjetas_amarillas": "2", "tarjetas_rojas": "0", "year": "2022"}], [{"nombre": "Christian Marrugo", "partidos_jugados": "42", "tarjetas_amarillas": "2", "tarjetas_rojas": "0", "year": "2022"}], [{"nombre": "Yuli\u00e1n G\u00f3mez", "partidos_jugados": "36", "tarjetas_amarillas": "2", "tarjetas_rojas": "0", "year": "2022"}], [{"nombre": "Luis V\u00e1squez", "partidos_jugados": "10", "tarjetas_amarillas": "2", "tarjetas_rojas": "0", "year": "2022"}], [{"nombre": "Johan Andr\u00e9s Mart\u00ednez", "partidos_jugados": "5", "tarjetas_amarillas": "1", "tarjetas_rojas": "0", "year": "2022"}], [{"nombre": "Jordy Monroy", "partidos_jugados": "15", "tarjetas_amarillas": "1", "tarjetas_rojas": "0", "year": "2022"}], [{"nombre": "Andr\u00e9s Alfonso", "partidos_jugados": "0", "tarjetas_amarillas": "0", "tarjetas_rojas": "0", "year": "2022"}], [{"nombre": "Weibmar Asprilla", "partidos_jugados": "0", "tarjetas_amarillas": "0", "tarjetas_rojas": "0", "year": "2022"}], [{"nombre": "Andres Cadavid", "partidos_jugados": "11", "tarjetas_amarillas": "4", "tarjetas_rojas": "1", "year": "2023"}], [{"nombre": "Daniel Torres", "partidos_jugados": "11", "tarjetas_amarillas": "3", "tarjetas_rojas": "0", "year": "2023"}], [{"nombre": "Jhon Palacios", "partidos_jugados": "10", "tarjetas_amarillas": "3", "tarjetas_rojas": "0", "year": "2023"}], [{"nombre": "Luciano Pons", "partidos_jugados": "12", "tarjetas_amarillas": "2", "tarjetas_rojas": "0", "year": "2023"}], [{"nombre": "Jaime Alvarado Hoyos", "partidos_jugados": "8", "tarjetas_amarillas": "2", "tarjetas_rojas": "0", "year": "2023"}], [{"nombre": "David Loaiza", "partidos_jugados": "8", "tarjetas_amarillas": "2", "tarjetas_rojas": "0", "year": "2023"}], [{"nombre": "Felipe Pardo", "partidos_jugados": "11", "tarjetas_amarillas": "2", "tarjetas_rojas": "0", "year": "2023"}], [{"nombre": "Jonathan Marulanda", "partidos_jugados": "6", "tarjetas_amarillas": "2", "tarjetas_rojas": "0", "year": "2023"}], [{"nombre": "Jordy Monroy", "partidos_jugados": "9", "tarjetas_amarillas": "2", "tarjetas_rojas": "0", "year": "2023"}], [{"nombre": "Daniel Londo\u00f1o", "partidos_jugados": "9", "tarjetas_amarillas": "2", "tarjetas_rojas": "0", "year": "2023"}], [{"nombre": "Victor Moreno", "partidos_jugados": "9", "tarjetas_amarillas": "2", "tarjetas_rojas": "0", "year": "2023"}], [{"nombre": "Deiner Qui\u00f1\u00f3nez", "partidos_jugados": "9", "tarjetas_amarillas": "1", "tarjetas_rojas": "0", "year": "2023"}], [{"nombre": "Miguel Monsalve", "partidos_jugados": "5", "tarjetas_amarillas": "1", "tarjetas_rojas": "0", "year": "2023"}], [{"nombre": "Andr\u00e9s Ricaurte", "partidos_jugados": "7", "tarjetas_amarillas": "1", "tarjetas_rojas": "0", "year": "2023"}], [{"nombre": "Juan David Arizala", "partidos_jugados": "1", "tarjetas_amarillas": "0", "tarjetas_rojas": "0", "year": "2023"}], [{"nombre": "Samir Mayo", "partidos_jugados": "1", "tarjetas_amarillas": "0", "tarjetas_rojas": "0", "year": "2023"}], [{"nombre": "Johan Andr\u00e9s Mart\u00ednez", "partidos_jugados": "1", "tarjetas_amarillas": "0", "tarjetas_rojas": "0", "year": "2023"}], [{"nombre": "Cristian Graciano", "partidos_jugados": "1", "tarjetas_amarillas": "0", "tarjetas_rojas": "0", "year": "2023"}], [{"nombre": "Juli\u00e1n Rodr\u00edguez", "partidos_jugados": "0", "tarjetas_amarillas": "0", "tarjetas_rojas": "0", "year": "2023"}], [{"nombre": "Andr\u00e9s Alfonso", "partidos_jugados": "1", "tarjetas_amarillas": "0", "tarjetas_rojas": "0", "year": "2023"}], [{"nombre": "Guillermo Tegue", "partidos_jugados": "1", "tarjetas_amarillas": "0", "tarjetas_rojas": "0", "year": "2023"}], [{"nombre": "Yuli\u00e1n G\u00f3mez", "partidos_jugados": "7", "tarjetas_amarillas": "0", "tarjetas_rojas": "0", "year": "2023"}], [{"nombre": "Brayan Ben\u00edtez", "partidos_jugados": "0", "tarjetas_amarillas": "0", "tarjetas_rojas": "0", "year": "2023"}], [{"nombre": "Andr\u00e9s Mosquera", "partidos_jugados": "10", "tarjetas_amarillas": "0", "tarjetas_rojas": "0", "year": "2023"}], [{"nombre": "Luis V\u00e1squez", "partidos_jugados": "4", "tarjetas_amarillas": "0", "tarjetas_rojas": "0", "year": "2023"}]]}